pyrostarter/__init__.py
pyrostarter/__main__.py
pyrostarter/commands/__init__.py
pyrostarter/commands/config.py
pyrostarter/commands/init.py
pyrostarter/constructor.py
pyrostarter/contents.py
pyrostarter/pyrostarter.py
pyrostarter-0.3.0.dist-info/entry_points.txt
pyrostarter-0.3.0.dist-info/LICENSE
pyrostarter-0.3.0.dist-info/WHEEL
pyrostarter-0.3.0.dist-info/METADATA
pyrostarter-0.3.0.dist-info/RECORD
