Metadata-Version: 2.1
Name: pyrostarter
Version: 0.3.0
Summary: Pyrogram CLI Template Creator
License: GNU General Public License v3 or later (GPLv3+)
Author: ahmetveburak
Author-email: ahmetbozyurtt@gmail.com
Requires-Python: >=3.6.2,<4.0.0
Classifier: License :: Other/Proprietary License
Classifier: Programming Language :: Python :: 3
Classifier: Programming Language :: Python :: 3.7
Classifier: Programming Language :: Python :: 3.8
Classifier: Programming Language :: Python :: 3.9
Classifier: Programming Language :: Python :: 3.10
Classifier: Programming Language :: Python :: 3.11
Requires-Dist: cleo (>=0.8.1,<0.9.0)
